[
  {
    "date": "February 6, 2026",
    "source": "The Vanguard",
    "source_url": "",
    "title": "Haffway - The Wither Tour"
  },
  {
    "date": "February 7, 2026",
    "source": "The Vanguard",
    "source_url": "",
    "title": "\u201cDad Rock Night\u201d (2000s Rock Tribute) presented by Council Hill"
  },
  {
    "date": "February 13, 2026",
    "source": "The Vanguard",
    "source_url": "",
    "title": "Straight Tequila Night ~ a Tribute to '90s Country (21+)"
  },
  {
    "date": "February 14, 2026",
    "source": "The Vanguard",
    "source_url": "",
    "title": "Through Being Cool Presents : Emo Valentines (18+)"
  },
  {
    "date": "February 15, 2026",
    "source": "The Vanguard",
    "source_url": "",
    "title": "Austin Meade"
  },
  {
    "date": "February 19, 2026",
    "source": "The Vanguard",
    "source_url": "",
    "title": "Tyler Hilton & Kate Voegele: Celebrating the Music of One Tree Hill"
  },
  {
    "date": "February 20, 2026",
    "source": "The Vanguard",
    "source_url": "",
    "title": "Pallbearer"
  },
  {
    "date": "friends February 21",
    "source": "The Vanguard",
    "source_url": "",
    "title": "Losing Connection & friends"
  },
  {
    "date": "February 22, 2026",
    "source": "The Vanguard",
    "source_url": "",
    "title": "Psychostick & Galactic Empire : The FATALI-TOUR"
  },
  {
    "date": "February 26, 2026",
    "source": "The Vanguard",
    "source_url": "",
    "title": "SOLD OUT | Logan Ryan Band"
  },
  {
    "date": "February 27, 2026",
    "source": "The Vanguard",
    "source_url": "",
    "title": "\u22c6\u02d9\u27e1 COTTAGE CHEMISTRY: A HEATED RIVALRY DANCE PARTY \u27e1\u02d9\u22c6 (18+)"
  },
  {
    "date": "February 28, 2026",
    "source": "The Vanguard",
    "source_url": "",
    "title": "Last Dinosaurs Wellness 10YR Anniversary Tour"
  },
  {
    "date": "March 5, 2026",
    "source": "The Vanguard",
    "source_url": "",
    "title": "Dan Kelly - The Anthem Tour"
  },
  {
    "date": "March 7, 2026",
    "source": "The Vanguard",
    "source_url": "",
    "title": "Tyler Farr"
  },
  {
    "date": "March 10, 2026",
    "source": "The Vanguard",
    "source_url": "",
    "title": "Lucero - Celebrating 20 Years of Nobody's Darlings"
  },
  {
    "date": "March 14, 2026",
    "source": "The Vanguard",
    "source_url": "",
    "title": "My So Called Band"
  },
  {
    "date": "March 15, 2026",
    "source": "The Vanguard",
    "source_url": "",
    "title": "cirKus"
  },
  {
    "date": "March 18, 2026",
    "source": "The Vanguard",
    "source_url": "",
    "title": "Winyah - No Place I'd Rather Be Tour"
  },
  {
    "date": "March 20, 2026",
    "source": "The Vanguard",
    "source_url": "",
    "title": "Flake"
  },
  {
    "date": "March 21, 2026",
    "source": "The Vanguard",
    "source_url": "",
    "title": "Emily Hollingshed"
  },
  {
    "date": "March 22, 2026",
    "source": "The Vanguard",
    "source_url": "",
    "title": "THE EARLY NOVEMBER & HELLOGOODBYE: 20 Years Young"
  },
  {
    "date": "March 24, 2026",
    "source": "The Vanguard",
    "source_url": "",
    "title": "Convictions + Wolves at the Gate - the Aftermath Tour"
  },
  {
    "date": "March 27, 2026",
    "source": "The Vanguard",
    "source_url": "",
    "title": "2 Minutes to Tulsa '26"
  },
  {
    "date": "April 3, 2026",
    "source": "The Vanguard",
    "source_url": "",
    "title": "2000's Rave - 18+"
  },
  {
    "date": "April 4, 2026",
    "source": "The Vanguard",
    "source_url": "",
    "title": "Josh Weathers"
  },
  {
    "date": "April 8, 2026",
    "source": "The Vanguard",
    "source_url": "",
    "title": "Stitched Up Heart"
  },
  {
    "date": "April 11, 2026",
    "source": "The Vanguard",
    "source_url": "",
    "title": "This Ain't a Scene - 18+ - MTV2 tribute"
  },
  {
    "date": "April 18, 2026",
    "source": "The Vanguard",
    "source_url": "",
    "title": "The Crane Wives - ACT I"
  },
  {
    "date": "April 21, 2026",
    "source": "The Vanguard",
    "source_url": "",
    "title": "Marlon Funaki - Half Moon Tour"
  },
  {
    "date": "April 22, 2026",
    "source": "The Vanguard",
    "source_url": "",
    "title": "James McMurtry and the Martial Law Review"
  },
  {
    "date": "April 26, 2026",
    "source": "The Vanguard",
    "source_url": "",
    "title": "Shovels & Rope"
  },
  {
    "date": "May 8, 2026",
    "source": "The Vanguard",
    "source_url": "",
    "title": "THE DOSE: A Psychedelic Comedy Show (18+)"
  },
  {
    "date": "May 9, 2026",
    "source": "The Vanguard",
    "source_url": "",
    "title": "Smells Like Nirvana"
  },
  {
    "date": "May 13, 2026",
    "source": "The Vanguard",
    "source_url": "",
    "title": "Ethan Regan - Spring Cleaning Tour"
  },
  {
    "date": "May 14, 2026",
    "source": "The Vanguard",
    "source_url": "",
    "title": "Citizen Soldier - Secret Songs tour Part II"
  },
  {
    "date": "May 18, 2026",
    "source": "The Vanguard",
    "source_url": "",
    "title": "Archspire: Long Roads Big Loads Tour"
  },
  {
    "date": "June 3, 2026",
    "source": "The Vanguard",
    "source_url": "",
    "title": "Bodysnatcher"
  },
  {
    "date": "June 5, 2026",
    "source": "The Vanguard",
    "source_url": "",
    "title": "Little Image"
  }
]